pandoc_compose/__init__.py
pandoc_compose/convert_task_callback.py
pandoc_compose/convert_task_glob_handler.py
pandoc_compose/errors.py
pandoc_compose/main.py
pandoc_compose/pandoc_compose_config.py
pandoc_compose/pandoc_config.py
pandoc_compose/utils.py
PandocCompose-0.0.9.dist-info/LICENSE
PandocCompose-0.0.9.dist-info/METADATA
PandocCompose-0.0.9.dist-info/WHEEL
PandocCompose-0.0.9.dist-info/entry_points.txt
PandocCompose-0.0.9.dist-info/top_level.txt
PandocCompose-0.0.9.dist-info/RECORD
