Metadata-Version: 2.1
Name: PandocCompose
Version: 0.0.9
Summary: PandocCompose lets you manage your documentation base using Pandoc
Home-page: https://gitlab.com/christophehenry/pandoc-compose
Author: Christophe Henry
Author-email: contact@c-henry.fr
License: UNKNOWN
Project-URL: Bug Tracker, https://gitlab.com/christophehenry/pandoc-compose/-/issues
Project-URL: Documentation, https://gitlab.com/christophehenry/pandoc-compose/-/tree/master/doc
Project-URL: Source Code, https://gitlab.com/christophehenry/pandoc-compose
Platform: UNKNOWN
Classifier: Programming Language :: Python :: 3.5
Classifier: Development Status :: 3 - Alpha
Classifier: License :: OSI Approved :: GNU General Public License v3 or later (GPLv3+)
Classifier: Operating System :: OS Independent
Classifier: Topic :: Text Processing :: General
Requires-Python: >=3.6
License-File: LICENSE
Requires-Dist: deepmerge (==0.1.0)
Requires-Dist: panflute (==1.12.5)
Requires-Dist: pypandoc (==1.5)
Requires-Dist: PyYAML (==5.3.1)
